{
  "IcoMoonType": "selection",
  "icons": [
    {
      "icon": {
        "paths": [
          "M742 376q-100-100-231-132t-255 10q96-12 211 37t213 147l-244 244q-98-98-147-213t-37-211q-42 124-10 255t132 231l-122 122q-126-126-126-305t126-305q0-2 2-2 140-140 336-124 162 12 274 124zM558 622l62-62 274 276-62 60z"
        ],
        "attrs": [
          {}
        ],
        "isMulticolor": false,
        "isMulticolor2": false,
        "tags": [
          "beach_access"
        ],
        "grid": 24
      },
      "attrs": [
        {}
      ],
      "properties": {
        "order": 1,
        "id": 0,
        "prevSize": 24,
        "name": "beach_access"
      },
      "setIdx": 0,
      "setId": 2,
      "iconIdx": 0
    }
  ],
  "height": 1024,
  "preferences": {
    "showGlyphs": true,
    "showQuickUse": true,
    "showQuickUse2": true,
    "showSVGs": true,
    "fontPref": {
      "prefix": "icon-",
      "metadata": {
        "fontFamily": "icomoon"
      },
      "metrics": {
        "emSize": 1024,
        "baseline": 6.25,
        "whitespace": 50
      },
      "embed": false
    },
    "imagePref": {
      "prefix": "icon-",
      "png": true,
      "useClassSelector": true,
      "color": 0,
      "bgColor": 16777215,
      "classSelector": ".icon",
      "name": "icomoon",
      "height": 32,
      "columns": 16,
      "margin": 16
    },
    "historySize": 50,
    "showCodes": true,
    "gridSize": 16
  }
}